{"engine": "tesseract", "max_dim": 960, "lang": "eng", "psm": 11, "image_hw": {"h": 1001, "w": 1440}, "words": [{"bbox_xywh": [64, 48, 34, 12], "text": "new", "conf": 0.9576117700000001}, {"bbox_xywh": [105, 46, 27, 14], "text": "tab", "conf": 0.9655201}, {"bbox_xywh": [1041, 183, 135, 54], "text": "se", "conf": 0.82312622}, {"bbox_xywh": [1338, 207, 38, 26], "text": "a", "conf": 0.6730238300000001}, {"bbox_xywh": [958, 267, 39, 12], "text": "alist", "conf": 0.25498075}, {"bbox_xywh": [1020, 267, 44, 10], "text": "what s", "conf": 0.65505577}, {"bbox_xywh": [1070, 267, 27, 10], "text": "new", "conf": 0.95497551}, {"bbox_xywh": [1128, 267, 60, 10], "text": "pessword", "conf": 0.28601818}, {"bbox_xywh": [1222, 267, 69, 10], "text": "downloads", "conf": 0.53824623}, {"bbox_xywh": [1318, 267, 44, 10], "text": "recent", "conf": 0.68900177}, {"bbox_xywh": [1366, 267, 30, 10], "text": "tabs", "conf": 0.68900177}, {"bbox_xywh": [1131, 282, 56, 14], "text": "manager", "conf": 0.9459047700000001}, {"bbox_xywh": [1000, 352, 39, 15], "text": "new", "conf": 0.9575990299999999}, {"bbox_xywh": [1046, 352, 33, 15], "text": "tab", "conf": 0.9575990299999999}, {"bbox_xywh": [592, 344, 254, 82], "text": "google", "conf": 0.9645184299999999}, {"bbox_xywh": [1000, 411, 39, 15], "text": "new", "conf": 0.96914467}, {"bbox_xywh": [1047, 411, 84, 20], "text": "incognito", "conf": 0.95428261}, {"bbox_xywh": [1137, 411, 33, 15], "text": "tab", "conf": 0.93498116}, {"bbox_xywh": [480, 472, 72, 16], "text": "search", "conf": 0.9697068}, {"bbox_xywh": [561, 477, 20, 12], "text": "or", "conf": 0.9663732899999999}, {"bbox_xywh": [588, 474, 45, 20], "text": "type", "conf": 0.96945679}, {"bbox_xywh": [642, 472, 42, 16], "text": "url", "conf": 0.96779732}, {"bbox_xywh": [948, 470, 10, 22], "text": "q", "conf": 0.41289558}, {"bbox_xywh": [1000, 470, 39, 15], "text": "new", "conf": 0.95882759}, {"bbox_xywh": [1046, 470, 74, 15], "text": "window", "conf": 0.9476226}, {"bbox_xywh": [519, 657, 18, 12], "text": "mr", "conf": 0.38131981000000004}, {"bbox_xywh": [874, 657, 27, 12], "text": "mit", "conf": 0.63262566}, {"bbox_xywh": [518, 676, 21, 12], "text": "wn", "conf": 0.26276865}, {"bbox_xywh": [999, 669, 48, 16], "text": "clear", "conf": 0.9614537}, {"bbox_xywh": [1053, 669, 84, 20], "text": "browsing", "conf": 0.92499489}, {"bbox_xywh": [1144, 670, 40, 15], "text": "data", "conf": 0.96922218}, {"bbox_xywh": [652, 734, 24, 24], "text": "8", "conf": 0.7933152}, {"bbox_xywh": [760, 735, 32, 22], "text": "a", "conf": 0.70949646}, {"bbox_xywh": [514, 795, 30, 9], "text": "what s", "conf": 0.7967883299999999}, {"bbox_xywh": [562, 796, 21, 8], "text": "new", "conf": 0.8858262600000001}, {"bbox_xywh": [626, 795, 30, 9], "text": "reading", "conf": 0.78801056}, {"bbox_xywh": [669, 796, 32, 10], "text": "list", "conf": 0.7795024100000001}, {"bbox_xywh": [738, 795, 42, 9], "text": "recent", "conf": 0.7021756}, {"bbox_xywh": [788, 795, 20, 9], "text": "tab", "conf": 0.73463196}, {"bbox_xywh": [867, 796, 44, 10], "text": "history", "conf": 0.44949157999999995}, {"bbox_xywh": [483, 860, 72, 12], "text": "discover", "conf": 0.8983158899999999}, {"bbox_xywh": [483, 920, 105, 21], "text": "something", "conf": 0.9630582400000001}, {"bbox_xywh": [594, 921, 48, 15], "text": "went", "conf": 0.9604361699999999}, {"bbox_xywh": [648, 924, 62, 16], "text": "wrong", "conf": 0.96172577}, {"bbox_xywh": [483, 958, 64, 12], "text": "couldn t", "conf": 0.68223503}, {"bbox_xywh": [554, 960, 63, 10], "text": "connect", "conf": 0.9475686600000001}, {"bbox_xywh": [622, 960, 15, 10], "text": "to", "conf": 0.9656713100000001}, {"bbox_xywh": [644, 958, 68, 12], "text": "discover", "conf": 0.95114288}, {"bbox_xywh": [720, 958, 24, 15], "text": "try", "conf": 0.9687263500000001}, {"bbox_xywh": [750, 962, 40, 12], "text": "again", "conf": 0.64386787}, {"bbox_xywh": [798, 958, 33, 12], "text": "later", "conf": 0.64386787}, {"bbox_xywh": [528, 984, 384, 8], "text": "pibnechinentatennshaiteltecatnesaen", "conf": 0.0}], "meta": {"available": true, "engine": "tesseract", "words": 52, "stderr": "Estimating resolution as 142"}}