{"engine": "easyocr", "max_dim": 1440, "lang": "eng", "psm": 11, "image_hw": {"h": 810, "w": 1440}, "words": [{"bbox_xywh": [8, 30, 26, 6], "text": "aart", "conf": 0.0010595228523015976}, {"bbox_xywh": [48, 28, 30, 8], "text": "mthaat", "conf": 0.0013675030712924933}, {"bbox_xywh": [92, 30, 26, 6], "text": "meet", "conf": 0.0013937992043793201}, {"bbox_xywh": [174, 30, 32, 8], "text": "chunm", "conf": 0.003727347962756471}, {"bbox_xywh": [220, 30, 22, 8], "text": "aapi", "conf": 0.0024939219001680613}, {"bbox_xywh": [258, 30, 30, 8], "text": "cuntarir", "conf": 0.03458254653328208}, {"bbox_xywh": [425, 27, 38, 14], "text": "aa", "conf": 0.06066298536611549}, {"bbox_xywh": [551, 27, 38, 14], "text": "0aa", "conf": 0.009012688723484112}, {"bbox_xywh": [844, 30, 38, 6], "text": "ee", "conf": 0.012402864624816903}, {"bbox_xywh": [886, 28, 40, 8], "text": "cametuneds", "conf": 0.0011564299162377526}, {"bbox_xywh": [930, 30, 38, 6], "text": "ken", "conf": 0.003153879676708831}, {"bbox_xywh": [1058, 27, 35, 12], "text": "qretw", "conf": 0.0016324232132237616}, {"bbox_xywh": [1098, 30, 40, 6], "text": "aoaeea", "conf": 8.936011127135614e-05}, {"bbox_xywh": [44, 40, 38, 6], "text": "mlnenela", "conf": 0.000130569255767275}, {"bbox_xywh": [174, 40, 30, 6], "text": "mietee", "conf": 0.00018917589750674574}, {"bbox_xywh": [930, 40, 38, 6], "text": "ueaa", "conf": 0.0016202020924538374}, {"bbox_xywh": [10, 80, 22, 8], "text": "e", "conf": 0.29672201481902505}, {"bbox_xywh": [46, 80, 34, 8], "text": "reneee", "conf": 0.003911049813698319}, {"bbox_xywh": [93, 79, 26, 12], "text": "ee0", "conf": 0.009023777199002776}, {"bbox_xywh": [128, 80, 38, 8], "text": "eoctlonn", "conf": 0.0066072911317626385}, {"bbox_xywh": [176, 80, 28, 8], "text": "bagoen", "conf": 0.0014755426092102567}, {"bbox_xywh": [218, 82, 26, 6], "text": "aeetae", "conf": 0.00032847439882176087}, {"bbox_xywh": [344, 80, 28, 8], "text": "flle", "conf": 0.0024073387030512094}, {"bbox_xywh": [1059, 79, 36, 12], "text": "oiea", "conf": 0.010671135038137436}, {"bbox_xywh": [1100, 80, 36, 8], "text": "sejrccci", "conf": 0.0003619889279941696}, {"bbox_xywh": [46, 90, 34, 8], "text": "uetenec", "conf": 0.0007070347538875471}, {"bbox_xywh": [178, 90, 22, 8], "text": "ka", "conf": 0.006871795782460192}, {"bbox_xywh": [1056, 90, 38, 8], "text": "ddenaln", "conf": 0.01219565629009132}, {"bbox_xywh": [624, 120, 30, 8], "text": "picicol1", "conf": 0.25403141556205444}, {"bbox_xywh": [658, 120, 104, 8], "text": "iditdu urll veve e", "conf": 0.0068291172452229175}, {"bbox_xywh": [768, 120, 42, 6], "text": "vecl701az", "conf": 0.010805345982280053}, {"bbox_xywh": [2, 128, 37, 14], "text": "yorct", "conf": 0.015960451893831957}, {"bbox_xywh": [46, 132, 34, 8], "text": "we", "conf": 0.01672620120061561}, {"bbox_xywh": [87, 131, 38, 12], "text": "fee", "conf": 0.04178678417194872}, {"bbox_xywh": [128, 132, 38, 8], "text": "klulu", "conf": 0.011015566307580249}, {"bbox_xywh": [722, 138, 26, 6], "text": "irerme", "conf": 0.0012903444327576241}, {"bbox_xywh": [760, 138, 26, 6], "text": "hamoloa", "conf": 0.001899085809985375}, {"bbox_xywh": [798, 138, 22, 6], "text": "lard", "conf": 0.005593398403444211}, {"bbox_xywh": [900, 136, 42, 8], "text": "ouck aecaas", "conf": 0.0011307856401071587}, {"bbox_xywh": [11, 141, 22, 12], "text": "eaja", "conf": 0.19251729547977448}, {"bbox_xywh": [1402, 154, 34, 8], "text": "detutlll", "conf": 0.04246065256362414}, {"bbox_xywh": [150, 166, 24, 6], "text": "cethnor", "conf": 0.07547658635588832}, {"bbox_xywh": [612, 172, 48, 8], "text": "hon nandaloi", "conf": 0.06315174109599428}, {"bbox_xywh": [754, 172, 64, 6], "text": "pemeen amaly", "conf": 0.0002491249111380224}, {"bbox_xywh": [822, 172, 30, 8], "text": "frpkclt", "conf": 0.031438025711142494}, {"bbox_xywh": [6, 184, 30, 6], "text": "ue", "conf": 0.0029246506082920877}, {"bbox_xywh": [48, 182, 30, 8], "text": "cal jn", "conf": 0.007210943000515332}, {"bbox_xywh": [622, 190, 66, 6], "text": "doomrct aamer", "conf": 0.0008703414566388621}, {"bbox_xywh": [306, 198, 50, 6], "text": "nm earanalen", "conf": 0.0059487920690192994}, {"bbox_xywh": [758, 196, 26, 6], "text": "krulcad", "conf": 0.0026132323438774353}, {"bbox_xywh": [938, 196, 30, 8], "text": "dalx", "conf": 0.22324572503566742}, {"bbox_xywh": [986, 196, 56, 6], "text": "eptecnmmmlan", "conf": 0.0013330879580653666}, {"bbox_xywh": [1074, 196, 24, 6], "text": "leax", "conf": 0.047092046588659286}, {"bbox_xywh": [148, 208, 52, 8], "text": "prolact setbnns", "conf": 0.18129549302318684}, {"bbox_xywh": [306, 208, 166, 8], "text": "3peul uanoue sanngs a88ectad impli merealiae", "conf": 0.003346302237185573}, {"bbox_xywh": [624, 216, 50, 8], "text": "piniegraiof", "conf": 0.32572973344101713}, {"bbox_xywh": [838, 214, 32, 6], "text": "entneale", "conf": 0.014088035194837872}, {"bbox_xywh": [990, 214, 30, 6], "text": "jrantan", "conf": 0.0032551400455414366}, {"bbox_xywh": [1030, 214, 36, 8], "text": "daer jio", "conf": 0.04807141592613625}, {"bbox_xywh": [158, 222, 26, 6], "text": "cenaa", "conf": 0.017767526558007948}, {"bbox_xywh": [776, 230, 50, 8], "text": "casion 30u c7", "conf": 0.027407463703209067}, {"bbox_xywh": [3, 233, 38, 12], "text": "xcnaa", "conf": 0.021404720964498056}, {"bbox_xywh": [158, 234, 34, 8], "text": "smulmjon", "conf": 0.12746708000938783}, {"bbox_xywh": [308, 240, 38, 6], "text": "congbainig", "conf": 0.060749901458151}, {"bbox_xywh": [622, 242, 42, 8], "text": "bilulatidh", "conf": 0.05353170545244565}, {"bbox_xywh": [776, 244, 36, 6], "text": "cenglain", "conf": 0.1964122632937308}, {"bbox_xywh": [992, 242, 26, 6], "text": "neitea", "conf": 0.008262808193431524}, {"bbox_xywh": [158, 248, 36, 6], "text": "flanolenn", "conf": 0.020157444881214594}, {"bbox_xywh": [158, 262, 32, 6], "text": "kinnineas", "conf": 0.012296288093944141}, {"bbox_xywh": [320, 258, 66, 6], "text": "denaunceremtaimiaal", "conf": 0.03493553258295906}, {"bbox_xywh": [406, 258, 24, 6], "text": "lonsut", "conf": 0.07913957788845438}, {"bbox_xywh": [440, 258, 22, 6], "text": "laca", "conf": 0.004068442620337009}, {"bbox_xywh": [650, 258, 34, 8], "text": "3ujaben", "conf": 0.07142750062861494}, {"bbox_xywh": [992, 260, 44, 8], "text": "fraed namte", "conf": 0.2931438414046259}, {"bbox_xywh": [1072, 260, 26, 8], "text": "polsd", "conf": 0.08783603817941311}, {"bbox_xywh": [776, 270, 44, 8], "text": "uulti souice", "conf": 0.16824589165568354}, {"bbox_xywh": [158, 276, 50, 6], "text": "kamaniauon", "conf": 0.32012530686514407}, {"bbox_xywh": [992, 274, 50, 8], "text": "fraaalazalan", "conf": 0.11705480213236606}, {"bbox_xywh": [1072, 274, 52, 8], "text": "dauisaproled", "conf": 0.10784449023726164}, {"bbox_xywh": [308, 280, 48, 6], "text": "aepanwpllolt", "conf": 0.018731709381852434}, {"bbox_xywh": [2, 286, 38, 6], "text": "etnreta", "conf": 0.00038114825395727024}, {"bbox_xywh": [49, 283, 30, 12], "text": "02", "conf": 0.0267578330695639}, {"bbox_xywh": [84, 281, 41, 14], "text": "eude", "conf": 0.02121853642165661}, {"bbox_xywh": [158, 288, 32, 8], "text": "lsbeam", "conf": 0.19783475767658762}, {"bbox_xywh": [622, 286, 48, 8], "text": "ril julys 3", "conf": 0.09705811109549382}, {"bbox_xywh": [992, 288, 46, 6], "text": "eeeancate", "conf": 0.00029616118855173794}, {"bbox_xywh": [1092, 288, 34, 6], "text": "wnccle", "conf": 0.009797864635306837}, {"bbox_xywh": [87, 293, 34, 12], "text": "gee", "conf": 0.013631571207031214}, {"bbox_xywh": [320, 296, 26, 8], "text": "3balc", "conf": 0.09965803796261337}, {"bbox_xywh": [366, 296, 186, 8], "text": "vz3 implaneaaban delautrepel ado imelemenzh", "conf": 0.04245439837950491}, {"bbox_xywh": [634, 302, 78, 8], "text": "onnelcarleddeslon", "conf": 0.10085204997209475}, {"bbox_xywh": [992, 300, 38, 8], "text": "fraad pan", "conf": 0.40186466486834577}, {"bbox_xywh": [1072, 300, 60, 8], "text": "uulc n6761 0", "conf": 0.06409341336291328}, {"bbox_xywh": [308, 318, 26, 6], "text": "uleanani", "conf": 0.01167936349794718}, {"bbox_xywh": [992, 314, 58, 8], "text": "top noolenat16", "conf": 0.03128609012440459}, {"bbox_xywh": [1072, 314, 38, 8], "text": "nul delned", "conf": 0.27774298397706126}, {"bbox_xywh": [148, 322, 42, 8], "text": "tod sctangs", "conf": 0.17177308392709406}, {"bbox_xywh": [646, 320, 62, 8], "text": "racen meteo logr", "conf": 0.06048153521402855}, {"bbox_xywh": [992, 328, 52, 8], "text": "targel ianquaji", "conf": 0.3358184914152957}, {"bbox_xywh": [1072, 328, 22, 8], "text": "venae", "conf": 0.18109633349666507}, {"bbox_xywh": [10, 336, 22, 8], "text": "otd", "conf": 0.011207894422113895}, {"bbox_xywh": [50, 336, 26, 8], "text": "uons", "conf": 0.007999219931662083}, {"bbox_xywh": [158, 334, 24, 8], "text": "prcad", "conf": 0.41733529466319375}, {"bbox_xywh": [646, 336, 38, 8], "text": "aecam dro", "conf": 0.046648558652189503}, {"bbox_xywh": [760, 334, 30, 6], "text": "hicalo", "conf": 0.20609154216624057}, {"bbox_xywh": [802, 334, 28, 6], "text": "ane", "conf": 0.016684781188652877}, {"bbox_xywh": [842, 334, 48, 6], "text": "comcatxdal", "conf": 0.023733094553090143}, {"bbox_xywh": [314, 342, 90, 6], "text": "uncremenlimeiemeniihdn", "conf": 0.023242116671388598}, {"bbox_xywh": [412, 342, 24, 6], "text": "teee", "conf": 0.004403115715831518}, {"bbox_xywh": [992, 342, 62, 6], "text": "kelmteualenanmuame", "conf": 0.0050135482840180535}, {"bbox_xywh": [158, 348, 34, 6], "text": "ipmcaum", "conf": 0.008850745267984956}, {"bbox_xywh": [646, 354, 34, 8], "text": "schamati", "conf": 0.4228562418501722}, {"bbox_xywh": [316, 362, 26, 8], "text": "uteedi", "conf": 0.06392582622163323}, {"bbox_xywh": [424, 362, 98, 6], "text": "khaidolimelemenbnonimeaut", "conf": 0.011581451718327565}, {"bbox_xywh": [758, 360, 80, 6], "text": "nnlneeeaemm annan", "conf": 0.00029795882642227715}, {"bbox_xywh": [158, 374, 24, 8], "text": "duclje", "conf": 0.1863187592325656}, {"bbox_xywh": [992, 374, 32, 6], "text": "suntezis", "conf": 0.016294264957230496}, {"bbox_xywh": [1210, 374, 50, 6], "text": "mmementadom", "conf": 0.44140196151244837}, {"bbox_xywh": [766, 378, 26, 6], "text": "nn", "conf": 0.023834503101246556}, {"bbox_xywh": [314, 382, 38, 8], "text": "pesocuon", "conf": 0.19669273413783353}, {"bbox_xywh": [412, 382, 110, 8], "text": "delaun sehngg or implemtchber", "conf": 0.007327292046717002}, {"bbox_xywh": [622, 382, 38, 8], "text": "bnthesis", "conf": 0.07321964793599822}, {"bbox_xywh": [94, 388, 22, 6], "text": "ktale", "conf": 0.006130960762939202}, {"bbox_xywh": [158, 388, 30, 6], "text": "kuentee", "conf": 0.0068380790983598875}, {"bbox_xywh": [992, 394, 22, 6], "text": "ehhs", "conf": 0.03808494284749031}, {"bbox_xywh": [1058, 394, 36, 6], "text": "ahehirad", "conf": 0.007055887797744159}, {"bbox_xywh": [1314, 394, 36, 6], "text": "hetehired", "conf": 0.03495750359035843}, {"bbox_xywh": [322, 400, 60, 8], "text": "deskn inbalzanon", "conf": 0.08929193003099838}, {"bbox_xywh": [398, 400, 26, 8], "text": "derain", "conf": 0.16637345192388012}, {"bbox_xywh": [650, 398, 30, 8], "text": "3ithegi", "conf": 0.12139445096679954}, {"bbox_xywh": [806, 400, 26, 8], "text": "gunhe1", "conf": 0.03491639370992273}, {"bbox_xywh": [992, 408, 34, 6], "text": "llperanee", "conf": 0.004038013098508738}, {"bbox_xywh": [1210, 408, 34, 6], "text": "wharranee", "conf": 0.010977437146678584}, {"bbox_xywh": [158, 414, 34, 8], "text": "teuf ferlu", "conf": 0.009601740529661996}, {"bbox_xywh": [634, 416, 82, 8], "text": "quen suttnased dasion", "conf": 0.024200883583605462}, {"bbox_xywh": [808, 418, 88, 8], "text": "quctujp 3070 1 3en40", "conf": 0.0035735133695895703}, {"bbox_xywh": [1058, 420, 60, 8], "text": "wo u3p k267o i e", "conf": 0.0047533957870149034}, {"bbox_xywh": [1314, 420, 60, 8], "text": "oju3 nagtb ite", "conf": 0.006004440027115301}, {"bbox_xywh": [158, 428, 64, 8], "text": "rdpan sinualons", "conf": 0.08966996624553679}, {"bbox_xywh": [326, 428, 24, 6], "text": "aemosl", "conf": 0.03863749597602086}, {"bbox_xywh": [762, 436, 38, 8], "text": "deeciipbon", "conf": 0.11374448359903258}, {"bbox_xywh": [806, 436, 82, 8], "text": "mnodo sircthesi celjuly", "conf": 0.028964121754081047}, {"bbox_xywh": [992, 434, 28, 8], "text": "suaienr", "conf": 0.04935621934954858}, {"bbox_xywh": [1060, 434, 80, 8], "text": "vread srmnesle calauna", "conf": 0.02778172400832319}, {"bbox_xywh": [1210, 434, 28, 8], "text": "saaqe", "conf": 0.06390330684444144}, {"bbox_xywh": [1316, 434, 98, 8], "text": "4040do imole meicalien dalauts", "conf": 0.030322378414266438}, {"bbox_xywh": [8, 440, 26, 6], "text": "et", "conf": 0.027032137102419928}, {"bbox_xywh": [158, 442, 22, 8], "text": "coti", "conf": 0.1463494896888733}, {"bbox_xywh": [322, 442, 76, 8], "text": "opidaalon det dasione", "conf": 0.017259780559677296}, {"bbox_xywh": [622, 444, 60, 8], "text": "wppldrrznt ti", "conf": 0.0059670123492774115}, {"bbox_xywh": [6, 448, 28, 8], "text": "mehien", "conf": 0.004884161358435637}, {"bbox_xywh": [992, 448, 50, 8], "text": "repod 3tueo", "conf": 0.08334686757365425}, {"bbox_xywh": [1058, 448, 40, 6], "text": "voostt", "conf": 0.032235443581923526}, {"bbox_xywh": [1114, 448, 48, 6], "text": "dlawepenone", "conf": 0.016923636075985658}, {"bbox_xywh": [1210, 448, 50, 8], "text": "repont 3balcj", "conf": 0.08166025890024725}, {"bbox_xywh": [1314, 448, 122, 6], "text": "vedomolenetatin elutrenods", "conf": 0.004313958338733567}, {"bbox_xywh": [158, 456, 50, 6], "text": "eledienrulee", "conf": 0.06840858936000349}, {"bbox_xywh": [332, 456, 30, 6], "text": "kenaeied", "conf": 0.051205340197980745}, {"bbox_xywh": [806, 454, 36, 8], "text": "nolbloi", "conf": 0.04133897605002057}, {"bbox_xywh": [634, 460, 64, 6], "text": "ennlmolemeneho", "conf": 0.011436965572713053}, {"bbox_xywh": [1210, 462, 58, 6], "text": "wmcementammele", "conf": 0.05420948377515791}, {"bbox_xywh": [1272, 462, 28, 6], "text": "lelmem", "conf": 0.09473642085743397}, {"bbox_xywh": [158, 470, 30, 6], "text": "rnoncue", "conf": 0.07240549025869891}, {"bbox_xywh": [634, 478, 56, 6], "text": "cnenlmnlemet", "conf": 0.009936953132098669}, {"bbox_xywh": [696, 478, 24, 6], "text": "wlleest", "conf": 0.015663496398232207}, {"bbox_xywh": [760, 478, 24, 6], "text": "gemer", "conf": 0.06982175934327099}, {"bbox_xywh": [796, 478, 32, 8], "text": "rropenas", "conf": 0.3277896510175774}, {"bbox_xywh": [842, 478, 24, 8], "text": "onone", "conf": 0.2711013025258808}, {"bbox_xywh": [902, 478, 26, 6], "text": "rerama", "conf": 0.13810112033537553}, {"bbox_xywh": [158, 482, 32, 8], "text": "sbaleje", "conf": 0.10165933325298238}, {"bbox_xywh": [326, 484, 22, 8], "text": "apost", "conf": 0.1938591557329124}, {"bbox_xywh": [6, 490, 30, 8], "text": "btau", "conf": 0.0029866299591958523}, {"bbox_xywh": [91, 489, 30, 12], "text": "jun", "conf": 0.10373316511684008}, {"bbox_xywh": [158, 496, 56, 8], "text": "winjw bertator", "conf": 0.010509749090902533}, {"bbox_xywh": [308, 496, 134, 6], "text": "edenoricrahoaein l3delennton", "conf": 0.0003174817424434764}, {"bbox_xywh": [622, 506, 76, 6], "text": "prccrnm derwg", "conf": 0.060845806271163205}, {"bbox_xywh": [758, 504, 36, 8], "text": "ciconsor", "conf": 0.08997231224141615}, {"bbox_xywh": [876, 506, 26, 6], "text": "renole", "conf": 0.18460636479102474}, {"bbox_xywh": [914, 504, 40, 8], "text": "dexon kung", "conf": 0.24905364716821363}, {"bbox_xywh": [634, 522, 62, 6], "text": "eenet nleaem", "conf": 0.00012727666755110235}, {"bbox_xywh": [84, 537, 41, 14], "text": "03sede", "conf": 0.0012987754647038948}, {"bbox_xywh": [634, 540, 80, 6], "text": "doen harcminthanaoer", "conf": 0.013982107535689127}, {"bbox_xywh": [818, 540, 36, 6], "text": "amalranl", "conf": 0.007734066428537057}, {"bbox_xywh": [1042, 540, 38, 6], "text": "wnclalpmne", "conf": 0.004020987205891721}, {"bbox_xywh": [1088, 540, 44, 6], "text": "eeuet rlmit", "conf": 0.00018300135836176162}, {"bbox_xywh": [1294, 540, 26, 6], "text": "elameen", "conf": 0.05133603057426919}, {"bbox_xywh": [1330, 540, 40, 8], "text": "run sbako", "conf": 0.1166690850353262}, {"bbox_xywh": [440, 554, 22, 8], "text": "canct", "conf": 0.1008196418698996}, {"bbox_xywh": [550, 556, 26, 6], "text": "besidie", "conf": 0.494997523474161}, {"bbox_xywh": [646, 556, 40, 8], "text": "cran taidel", "conf": 0.21724165329056525}, {"bbox_xywh": [818, 554, 24, 6], "text": "cpnati", "conf": 0.07585790627987643}, {"bbox_xywh": [864, 554, 36, 6], "text": "lnsnad", "conf": 0.005805854850948309}, {"bbox_xywh": [1330, 552, 104, 8], "text": "vuado enbeils delallb gnado", "conf": 0.042538677155663174}, {"bbox_xywh": [818, 568, 24, 6], "text": "conate", "conf": 0.1000049048650105}, {"bbox_xywh": [864, 568, 36, 6], "text": "ndaaad", "conf": 0.030547071760769394}, {"bbox_xywh": [1330, 566, 98, 8], "text": "vuaca mnhamantalon delalil", "conf": 0.040061932029246954}, {"bbox_xywh": [646, 574, 50, 8], "text": "prgrmdeazc", "conf": 0.22294652440852325}, {"bbox_xywh": [433, 581, 174, 14], "text": "mrereens 5t5718242a 02e70jz7", "conf": 7.391782536748939e-05}, {"bbox_xywh": [646, 590, 100, 8], "text": "f comqunalii nenenneel", "conf": 0.036702081862049526}, {"bbox_xywh": [451, 617, 68, 14], "text": "waeriar", "conf": 0.035848504287668295}, {"bbox_xywh": [2, 644, 38, 6], "text": "mhneen", "conf": 0.002839507106848505}, {"bbox_xywh": [451, 643, 68, 12], "text": "rukeui3", "conf": 0.03090380943582256}, {"bbox_xywh": [452, 656, 56, 8], "text": "qabnrt", "conf": 0.007432365350531583}, {"bbox_xywh": [512, 656, 58, 6], "text": "clecatn", "conf": 0.0012152645250230007}, {"bbox_xywh": [438, 734, 48, 8], "text": "halerei", "conf": 0.002105638741002075}, {"bbox_xywh": [492, 734, 40, 8], "text": "hakaf", "conf": 0.0070767865678114175}, {"bbox_xywh": [542, 734, 42, 6], "text": "veatd", "conf": 0.0023364042709218135}, {"bbox_xywh": [183, 789, 42, 16], "text": "n", "conf": 0.9530155194980239}, {"bbox_xywh": [1348, 792, 24, 8], "text": "vla", "conf": 0.029800722586689705}, {"bbox_xywh": [136, 138, 21, 13], "text": "e", "conf": 0.6815254541220952}], "meta": {"available": true, "engine": "easyocr", "langs": ["en"], "gpu": false, "reader_cached": true, "words": 210}}