{"engine": "easyocr", "max_dim": 960, "lang": "eng", "psm": 11, "image_hw": {"h": 3200, "w": 1440}, "words": [{"bbox_xywh": [63, 43, 133, 53], "text": "10 57", "conf": 0.9264690056513175}, {"bbox_xywh": [930, 37, 453, 67], "text": "rek hrii 3 c d69", "conf": 0.009718007583091093}, {"bbox_xywh": [380, 180, 693, 107], "text": "xiaomi account", "conf": 0.9910743098703347}, {"bbox_xywh": [1267, 187, 93, 87], "text": "83", "conf": 0.5093863744391958}, {"bbox_xywh": [260, 873, 287, 100], "text": "xiaomi", "conf": 0.6523129651106828}, {"bbox_xywh": [837, 897, 100, 67], "text": "m", "conf": 0.38207868952455115}, {"bbox_xywh": [963, 827, 293, 123], "text": "family", "conf": 0.6894505860995385}, {"bbox_xywh": [977, 957, 273, 67], "text": "invite me", "conf": 0.8991501471877873}, {"bbox_xywh": [107, 1133, 287, 87], "text": "occupied", "conf": 0.9672675537900308}, {"bbox_xywh": [973, 1173, 260, 100], "text": "find d", "conf": 0.9989324792869547}, {"bbox_xywh": [107, 1240, 527, 107], "text": "0 9 gb 5 gb", "conf": 0.5910458277704984}, {"bbox_xywh": [973, 1287, 107, 80], "text": "on", "conf": 0.9998079000691638}, {"bbox_xywh": [100, 1620, 393, 80], "text": "my account", "conf": 0.9997181519967246}, {"bbox_xywh": [100, 1800, 327, 87], "text": "account", "conf": 0.7544369097864766}, {"bbox_xywh": [653, 1850, 593, 97], "text": "add recovery info", "conf": 0.9942051881734375}, {"bbox_xywh": [87, 1883, 333, 127], "text": "security", "conf": 0.9999604237848592}, {"bbox_xywh": [90, 2117, 210, 123], "text": "help", "conf": 0.9999726414680481}, {"bbox_xywh": [747, 2130, 533, 97], "text": "reset password", "conf": 0.9999939465797179}, {"bbox_xywh": [100, 2353, 320, 93], "text": "devices", "conf": 0.9999964405047267}, {"bbox_xywh": [100, 2580, 860, 93], "text": "about xiaomi account", "conf": 0.9073637828713715}, {"bbox_xywh": [547, 2877, 337, 133], "text": "sign out", "conf": 0.9580153274727765}], "meta": {"available": true, "engine": "easyocr", "langs": ["en"], "gpu": false, "reader_cached": true, "words": 21}}